Metadata-Version: 1.2
Name: amdgpu-fan
Version: 0.0.5.post1555641211
Summary: amdgpu fan controller
Home-page: https://github.com/chestm007/amdgpu-fan
Author: Max Chesterfield
Author-email: chestm007@hotmail.com
Maintainer: Max Chesterfield
Maintainer-email: chestm007@hotmail.com
License: GPL-2.0
Platform: UNKNOWN
